Buzzer_As_A_Service
