Metadata-Version: 1.0
Name: buzzer-as-a-service
Version: 0.1.2
Summary: IRC Bot to play an audible buzzer sound
Home-page: https://github.com/liam-middlebrook/buzzer-as-a-service
Author: Liam Middlebrook
Author-email: liammiddlebrook@gmail.com
License: MIT License
Keywords: IRC pyAudio
Platform: UNKNOWN
